setup.py
digLandmarkExtractor/__init__.py
digLandmarkExtractor/dig_landmark_extractor.py
digLandmarkExtractor/dig_multiplexing_landmark_extractor.py
digLandmarkExtractor/get_landmark_extractor_processors.py
digLandmarkExtractor.egg-info/PKG-INFO
digLandmarkExtractor.egg-info/SOURCES.txt
digLandmarkExtractor.egg-info/dependency_links.txt
digLandmarkExtractor.egg-info/requires.txt
digLandmarkExtractor.egg-info/top_level.txt
test/test_landmark_extractor.py