Metadata-Version: 1.1
Name: digLandmarkExtractor
Version: 0.3.0
Summary: digLandmarkExtractor
Home-page: https://github.com/usc-isi-i2/dig-landmark-extractor
Author: Jason Slepicka
Author-email: jasonslepicka@gmail.com
License: UNKNOWN
Download-URL: https://github.com/usc-isi-i2/dig-landmark-extractor
Platform: UNKNOWN
